Workbook
Name rendimento_carteira: PRINCIPAL!$C$12

Sheet PRINCIPAL
B10: CONFIGURAÇÕES
B11: Salário | C11: 1621
B12: Rendimento Carteira | C12: 0.01
B13: Sugestão de Investimentos | C13: =C11*30% -> 486.3
B15: INVESTIMENTO MENSAL
B16: Quanto devo investir por mês? | C16: 100
B17: Por quanto anos? | C17: 10
B18: Qual a taxa de rendimento mensal? | C18: 0.01079
B19: Quanto patrimônio aumentado terei? | C19: =FV(C18,C17*12,C16*-1) -> 24328.421
B20: Qual o dividendo por mês? | C20: =C19*C12 -> 243.28421
B23: CENÁRIOS
A24: 2 | B24: Quanto em 2 anos? | C24: =FV($C$18,$A24*12,$C$16*-1) -> 2722.7627 | D24: =C24*$C$12 -> 27.227627
A25: 5 | B25: Quantos em 5 anos? | C25: =FV($C$18,$A25*12,$C$16*-1) -> 8377.6914 | D25: =C25*$C$12 -> 83.776914
A26: 10 | B26: Quantos em 10 anos? | C26: =FV($C$18,$A26*12,$C$16*-1) -> 24328.421 | D26: =C26*$C$12 -> 243.28421
A27: 20 | B27: Quantos em 20 anos? | C27: =FV($C$18,$A27*12,$C$16*-1) -> 112519.84 | D27: =C27*$C$12 -> 1125.1984
A28: 30 | B28: Quantos em 30 anos ? | C28: =FV($C$18,$A28*12,$C$16*-1) -> 432216.97 | D28: =C28*$C$12 -> 4322.1697
B32: Perfil | C32: CONSERVADOR
B33: Valor a ser investido por mês? | C33: =C16 -> 100
B36: TIPOS DE FII | C36: PERCENTUAL SUGERIDO | D36: VALORES
B37: PAPEL | C37: =VLOOKUP($C$32&"-"&B37,Apoio!$A:$D,4,FALSE) -> 0.3 | D37: =C37*$C$33 -> 30
B38: TIJOLO | C38: =VLOOKUP($C$32&"-"&B38,Apoio!$A:$D,4,FALSE) -> 0.5 | D38: =C38*$C$33 -> 50
B39: HÍBRIDOS | C39: =VLOOKUP($C$32&"-"&B39,Apoio!$A:$D,4,FALSE) -> 0.1 | D39: =C39*$C$33 -> 10
B40: FOFs | C40: =VLOOKUP($C$32&"-"&B40,Apoio!$A:$D,4,FALSE) -> 0.1 | D40: =C40*$C$33 -> 10
B41: DESENVOLVIMENTO | C41: =VLOOKUP($C$32&"-"&B41,Apoio!$A:$D,4,FALSE) -> 0 | D41: =C41*$C$33 -> 0
B42: HOTELARIA | C42: =VLOOKUP($C$32&"-"&B42,Apoio!$A:$D,4,FALSE) -> 0 | D42: =C42*$C$33 -> 0
C43: TOTAL | D43: =SUM(D37:D42) -> 100
B46: SIMULAÇÃO
B47: FIIs escolhida | C47: MXRF11
B48: Valor atual da Cota | C48: =VLOOKUP(C47,Apoio!G:J,3,FALSE) -> 9.54
B49: DIVIDEN YIED | C49: =VLOOKUP(C47,Apoio!G5:M10,4,FALSE) -> 0.0101
B50: Quantidade de Cotas por mês | C50: 5
B51: Tempo de Investimento em anos | C51: 1
B54: RESULTADO
B55: DATA DA COMPRA | C55: 46024
B56: VALOR INVESTIDO POR MÊS | C56: =C48*C50 -> 47.7
B57: VALOR INVESTIDO POR ANO | C57: =C56*(C51*12) -> 572.4
B58: DIVIDENDO POR MÊS | C58: =C56*C49 -> 0.48177
B59: DIVIDENDO POR ANO | C59: =FV(C49,C51*12,C56*-1) -> 605.29204
B60: GANHO EM REAIS | C60: =C59-C57 -> 32.892038

Sheet Apoio
F3: CARTEIRA DE INVESTMENTOS
F4: INVESTIMENTO EM QUANTOS ANOS: | K4: 1
A5: CHAVE | B5: PERFIL | C5: TIPOS DE FII | D5: PERCENTUAL | F5: DATA DA COMPRA | G5: FIIs | H5: TIPO | I5: COTA ATUAL | J5: DIVIDEND YIED | K5: QUANTIDADE DE COTAS | L5: INVESTIMENTO MENSAL | M5: RENDIMENTO MENSAL
A6: =$B$6&"-"&C6 -> CONSERVADOR-PAPEL | B6: CONSERVADOR | C6: PAPEL | D6: 0.3 | F6: 46020 | G6: MXRF11 | H6: PAPEL | I6: 9.54 | J6: 0.0101 | K6: 10 | L6: =I6*K6 -> 95.4 | M6: =I6*J6*K6 -> 0.96354
A7: =$B$6&"-"&C7 -> CONSERVADOR-TIJOLO | B7: CONSERVADOR | C7: TIJOLO | D7: 0.5 | F7: 46024 | G7: MXRF11 | H7: PAPEL | I7: 9.56 | J7: 0.0101 | K7: 10 | L7: =I7*K7 -> 95.6 | M7: =I7*J7*K7 -> 0.96556
A8: =$B$6&"-"&C8 -> CONSERVADOR-HÍBRIDOS | B8: CONSERVADOR | C8: HÍBRIDOS | D8: 0.1 | F8: 46024 | G8: RZAK11 | H8: PAPEL | I8: 82.45 | J8: 0.0094 | K8: 1 | L8: =I8*K8 -> 82.45 | M8: =I8*J8*K8 -> 0.77503
A9: =$B$6&"-"&C9 -> CONSERVADOR-FOFs | B9: CONSERVADOR | C9: FOFs | D9: 0.1 | F9: 46024 | G9: PSEC11 | H9: PAPEL | I9: 43.31 | J9: 0.0087 | K9: 1 | L9: =I9*K9 -> 43.31 | M9: =I9*J9*K9 -> 0.376797
A10: =$B$6&"-"&C10 -> CONSERVADOR-DESENVOLVIMENTO | B10: CONSERVADOR | C10: DESENVOLVIMENTO | D10: 0 | G10: CARTEIRA | I10: =SUM(I6:I9) -> 144.86 | J10: =AVERAGE(J6:J9) -> 0.009575 | K10: =SUM(K6:K9) -> 22 | L10: =SUM(L6:L9) -> 316.76 | M10: =SUM(M6:M9) -> 3.080927
A11: =$B$6&"-"&C11 -> CONSERVADOR-HOTELARIA | B11: CONSERVADOR | C11: HOTELARIA | D11: 0
A12: =$B$12&"-"&C12 -> MODERADO-PAPEL | B12: MODERADO | C12: PAPEL | D12: 0.32
A13: =$B$12&"-"&C13 -> MODERADO-TIJOLO | B13: MODERADO | C13: TIJOLO | D13: 0.35
A14: =$B$12&"-"&C14 -> MODERADO-HÍBRIDOS | B14: MODERADO | C14: HÍBRIDOS | D14: 0.08
A15: =$B$12&"-"&C15 -> MODERADO-FOFs | B15: MODERADO | C15: FOFs | D15: 0.05
A16: =$B$12&"-"&C16 -> MODERADO-DESENVOLVIMENTO | B16: MODERADO | C16: DESENVOLVIMENTO | D16: 0.1
A17: =$B$12&"-"&C17 -> MODERADO-HOTELARIA | B17: MODERADO | C17: HOTELARIA | D17: 0.1
A18: =$B$18&"-"&C18 -> AGRESSIVO-PAPEL | B18: AGRESSIVO | C18: PAPEL | D18: 0.5
A19: =$B$18&"-"&C19 -> AGRESSIVO-TIJOLO | B19: AGRESSIVO | C19: TIJOLO | D19: 0.1
A20: =$B$18&"-"&C20 -> AGRESSIVO-HÍBRIDOS | B20: AGRESSIVO | C20: HÍBRIDOS | D20: 0.05
A21: =$B$18&"-"&C21 -> AGRESSIVO-FOFs | B21: AGRESSIVO | C21: FOFs | D21: 0.05
A22: =$B$18&"-"&C22 -> AGRESSIVO-DESENVOLVIMENTO | B22: AGRESSIVO | C22: DESENVOLVIMENTO | D22: 0.2
A23: =$B$18&"-"&C23 -> AGRESSIVO-HOTELARIA | B23: AGRESSIVO | C23: HOTELARIA | D23: 0.1
